{
  "v": 1,
  "shard": "u",
  "type": "track",
  "updated_at": "2026-05-19T09:00:48.355Z",
  "entries": [
    {
      "hash": "200ecb8087e8e798",
      "track": "Un Ka Andaz-E-Karam (Complete Original Version)",
      "artist": "Nusrat Fateh Ali Khan – Eternal Qawwali & Sufi Classics",
      "album": "Nusrat Fateh Ali Khan – Eternal Qawwali & Sufi Classics",
      "has_synced": false,
      "has_plain": true,
      "cached_at": "2026-03-12T01:44:06.254Z"
    },
    {
      "hash": "c4f231db5704229d",
      "track": "Uska Hi Banana",
      "artist": "Arijit Singh",
      "album": "1920 Evil Returns",
      "has_synced": true,
      "has_plain": false,
      "cached_at": "2026-03-28T12:46:15.564Z"
    },
    {
      "hash": "d3af3b01bbf97b0a",
      "track": "Ude Dil Befikre",
      "artist": "Vishal & Shekhar, Benny Dayal, Sophie Choudry, Jaideep Sahni",
      "album": "Befikre",
      "has_synced": true,
      "has_plain": true,
      "cached_at": "2026-05-19T09:00:46.429Z"
    }
  ]
}